sample/__init__.py
sample/package_data.dat
sample/simple.py
samplepebblo-3.0.4.dist-info/METADATA
samplepebblo-3.0.4.dist-info/WHEEL
samplepebblo-3.0.4.dist-info/entry_points.txt
samplepebblo-3.0.4.dist-info/top_level.txt
samplepebblo-3.0.4.dist-info/RECORD
